pocbot/__init__.py
pocbot/chain_templates.py
pocbot/ui_templates.py
pocbot-0.3.0.dist-info/METADATA
pocbot-0.3.0.dist-info/WHEEL
pocbot-0.3.0.dist-info/RECORD
