Metadata-Version: 2.1
Name: pocbot
Version: 0.3.0
Summary: Easy Streamlit UI template for ChatBots
Home-page: https://github.com/thisisqubika/pocbot
License: MIT
Author: Ezequiel Panzarasa
Author-email: ezequiel.panzarasa@qubika.com
Requires-Python: >=3.8, !=2.7.*, !=3.0.*, !=3.1.*, !=3.2.*, !=3.3.*, !=3.4.*, !=3.5.*, !=3.6.*, !=3.7.*
Classifier: License :: OSI Approved :: MIT License
Classifier: Programming Language :: Python :: 3
Classifier: Programming Language :: Python :: 3.8
Classifier: Programming Language :: Python :: 3.9
Classifier: Programming Language :: Python :: 3.10
Classifier: Programming Language :: Python :: 3.11
Requires-Dist: streamlit (>=1.29.0,<2.0.0)
Project-URL: Repository, https://github.com/thisisqubika/pocbot
